src/__init__.py
src/plugin.py
mkdocs_plugin_inline_svg_utf8-0.1.3.dist-info/LICENSE.md
mkdocs_plugin_inline_svg_utf8-0.1.3.dist-info/METADATA
mkdocs_plugin_inline_svg_utf8-0.1.3.dist-info/WHEEL
mkdocs_plugin_inline_svg_utf8-0.1.3.dist-info/entry_points.txt
mkdocs_plugin_inline_svg_utf8-0.1.3.dist-info/top_level.txt
mkdocs_plugin_inline_svg_utf8-0.1.3.dist-info/RECORD
