Metadata-Version: 2.1
Name: mkdocs-plugin-inline-svg-utf8
Version: 0.1.3
Summary: A MkDocs plugin that inlines SVG images into the output with utf-8 encoding.
Home-page: https://github.com/Grufbert/mkdocs-plugin-inline-svg-utf8
Author: Nico Klinger
License: MIT
Keywords: mkdocs plugin inline svg utf8
Requires-Python: >=3.5
License-File: LICENSE.md
Requires-Dist: mkdocs
